adapter/DefaultGraph.py
adapter/GraphToMermaidAdapter.py
adapter/MermaidAdapter.py
adapter/MermaidToGraphAdapter.py
adapter/Parser.py
adapter/__init__.py
adapter/main.py
adapter/utils.py
GraphToMermaid-0.1.3.dist-info/METADATA
GraphToMermaid-0.1.3.dist-info/WHEEL
GraphToMermaid-0.1.3.dist-info/top_level.txt
GraphToMermaid-0.1.3.dist-info/RECORD
