Metadata-Version: 2.1
Name: GraphToMermaid
Version: 0.1.3
Summary: Convert any graph like structure to a mermaid and vice versa
Home-page: https://github.com/huynd2210/GraphToMermaid
Author: huynd2210
Classifier: Programming Language :: Python :: 3
Classifier: License :: OSI Approved :: MIT License
Classifier: Operating System :: OS Independent
Requires-Python: >=3.6
Requires-Dist: mermaid-builder
